btb_judge/__init__.py
btb_judge/constants.py
btb_judge/judge.py
btb_judge/main.py
btb_judge/serializers.py
btb_judge-0.1.4.dist-info/entry_points.txt
btb_judge-0.1.4.dist-info/WHEEL
btb_judge-0.1.4.dist-info/METADATA
btb_judge-0.1.4.dist-info/RECORD
